setup.py
binarysearchtree/__init__.py
binarysearchtree/my_basic_bst.py
my_basic_bst.egg-info/PKG-INFO
my_basic_bst.egg-info/SOURCES.txt
my_basic_bst.egg-info/dependency_links.txt
my_basic_bst.egg-info/not-zip-safe
my_basic_bst.egg-info/top_level.txt