Metadata-Version: 2.1
Name: my-basic-bst
Version: 0.1
Summary: binary search tree implementation with all basic methods
Home-page: UNKNOWN
Author: maslenchenko oleksandra
License: UNKNOWN
Platform: UNKNOWN
